{
    "family": "invited_cmds",
    "cmds": [
        {
            "label": "Ping",
            "req": {
                "cmd": "ping",
                "other_fields": [
                    {
                        "name": "ping",
                        "type": "String"
                    }
                ]
            },
            "reps": [
                {
                    "status": "ok",
                    "other_fields": [
                        {
                            "name": "pong",
                            "type": "String"
                        }
                    ]
                }
            ]
        },
        {
            "label": "InviteInfo",
            "req": {
                "cmd": "invite_info",
                "other_fields": []
            },
            "reps": [
                {
                    "status": "ok",
                    "unit": "UserOrDevice",
                    "other_fields": []
                }
            ],
            "nested_types": [
                {
                    "label": "UserOrDevice",
                    "tag": "type",
                    "variants": [
                        {
                            "name": "User",
                            "discriminant_value": "USER",
                            "fields": [
                                {
                                    "name": "claimer_email",
                                    "type": "String"
                                },
                                {
                                    "name": "greeter_user_id",
                                    "type": "UserID"
                                },
                                {
                                    "name": "greeter_human_handle",
                                    "type": "HumanHandle"
                                }
                            ]
                        },
                        {
                            "name": "Device",
                            "discriminant_value": "DEVICE",
                            "fields": [
                                {
                                    "name": "greeter_user_id",
                                    "type": "UserID"
                                },
                                {
                                    "name": "greeter_human_handle",
                                    "type": "HumanHandle"
                                }
                            ]
                        }
                    ]
                }
            ]
        },
        {
            "label": "Invite1ClaimerWaitPeer",
            "req": {
                "cmd": "invite_1_claimer_wait_peer",
                "other_fields": [
                    {
                        "name": "claimer_public_key",
                        "type": "PublicKey"
                    }
                ]
            },
            "reps": [
                {
                    "status": "ok",
                    "other_fields": [
                        {
                            "name": "greeter_public_key",
                            "type": "PublicKey"
                        }
                    ]
                },
                {
                    "status": "not_found",
                    "other_fields": []
                },
                {
                    "status": "invalid_state",
                    "other_fields": []
                }
            ]
        },
        {
            "label": "Invite2aClaimerSendHashedNonceHashNonce",
            "req": {
                "cmd": "invite_2a_claimer_send_hashed_nonce_hash_nonce",
                "other_fields": [
                    {
                        "name": "claimer_hashed_nonce",
                        "type": "HashDigest"
                    }
                ]
            },
            "reps": [
                {
                    "status": "ok",
                    "other_fields": [
                        {
                            "name": "greeter_nonce",
                            "type": "Bytes"
                        }
                    ]
                },
                {
                    "status": "not_found",
                    "other_fields": []
                },
                {
                    "status": "already_deleted",
                    "other_fields": []
                },
                {
                    "status": "invalid_state",
                    "other_fields": []
                }
            ]
        },
        {
            "label": "Invite2bClaimerSendNonce",
            "req": {
                "cmd": "invite_2b_claimer_send_nonce",
                "other_fields": [
                    {
                        "name": "claimer_nonce",
                        "type": "Bytes"
                    }
                ]
            },
            "reps": [
                {
                    "status": "ok",
                    "other_fields": []
                },
                {
                    "status": "not_found",
                    "other_fields": []
                },
                {
                    "status": "invalid_state",
                    "other_fields": []
                }
            ]
        },
        {
            "label": "Invite3aClaimerSignifyTrust",
            "req": {
                "cmd": "invite_3a_claimer_signify_trust",
                "other_fields": []
            },
            "reps": [
                {
                    "status": "ok",
                    "other_fields": []
                },
                {
                    "status": "not_found",
                    "other_fields": []
                },
                {
                    "status": "invalid_state",
                    "other_fields": []
                }
            ]
        },
        {
            "label": "Invite3bClaimerWaitPeerTrust",
            "req": {
                "cmd": "invite_3b_claimer_wait_peer_trust",
                "other_fields": []
            },
            "reps": [
                {
                    "status": "ok",
                    "other_fields": []
                },
                {
                    "status": "not_found",
                    "other_fields": []
                },
                {
                    "status": "invalid_state",
                    "other_fields": []
                }
            ]
        },
        {
            "label": "Invite4ClaimerCommunicate",
            "req": {
                "cmd": "invite_4_claimer_communicate",
                "other_fields": [
                    {
                        "name": "payload",
                        "type": "Bytes"
                    }
                ]
            },
            "reps": [
                {
                    "status": "ok",
                    "other_fields": [
                        {
                            "name": "payload",
                            "type": "Bytes"
                        }
                    ]
                },
                {
                    "status": "not_found",
                    "other_fields": []
                },
                {
                    "status": "invalid_state",
                    "other_fields": []
                }
            ]
        }
    ]
}
